dwavetuner/__init__.py
dwavetuner/job.py
dwavetuner/scanner.py
dwavetuner/utils.py
dwave_tuner-0.0.4.dist-info/METADATA
dwave_tuner-0.0.4.dist-info/WHEEL
dwave_tuner-0.0.4.dist-info/top_level.txt
dwave_tuner-0.0.4.dist-info/RECORD
