Metadata-Version: 2.1
Name: dwave-tuner
Version: 0.0.4
Summary: Tune D-Wave QPU solver parameters
Author-email: Orkun Şensebat <git@senseb.at>
Project-URL: Repository, https://jugit.fz-juelich.de/qip/dwave-tuner
Project-URL: Issues, https://jugit.fz-juelich.de/qip/dwave-tuner/-/issues
Requires-Python: >=3.7
